LICENSE
MANIFEST.in
readme.md
requirements.txt
setup.cfg
setup.py
algen/__init__.py
algen/compilers.py
algen/consts.py
algen.egg-info/PKG-INFO
algen.egg-info/SOURCES.txt
algen.egg-info/dependency_links.txt
algen.egg-info/entry_points.txt
algen.egg-info/not-zip-safe
algen.egg-info/requires.txt
algen.egg-info/top_level.txt
algen/scripts/__init__.py
algen/scripts/cli.py
algen/templates/AlchemyTemplate.py
algen/templates/__init__.py
algen/templates/funcs.py
algen/templates/orm.py
algen/templates/statements.py