Metadata-Version: 1.1
Name: algen
Version: 1.0.3
Summary: algen
Home-page: https://github.com/danishabdullah/algen
Author: Danish Abdullah
Author-email: dev@danishabdullah.com
License: The MIT License (MIT)
